odoo/addons/sale_loyalty_limit/README.rst
odoo/addons/sale_loyalty_limit/__init__.py
odoo/addons/sale_loyalty_limit/__manifest__.py
odoo/addons/sale_loyalty_limit/i18n/it.po
odoo/addons/sale_loyalty_limit/i18n/sale_coupon_limit.pot
odoo/addons/sale_loyalty_limit/i18n/sale_loyalty_limit.pot
odoo/addons/sale_loyalty_limit/models/__init__.py
odoo/addons/sale_loyalty_limit/models/loyalty_program.py
odoo/addons/sale_loyalty_limit/models/sale_order.py
odoo/addons/sale_loyalty_limit/readme/CONFIGURE.md
odoo/addons/sale_loyalty_limit/readme/CONTRIBUTORS.md
odoo/addons/sale_loyalty_limit/readme/DESCRIPTION.md
odoo/addons/sale_loyalty_limit/readme/USAGE.md
odoo/addons/sale_loyalty_limit/security/ir.model.access.csv
odoo/addons/sale_loyalty_limit/static/description/icon.png
odoo/addons/sale_loyalty_limit/static/description/icon.svg
odoo/addons/sale_loyalty_limit/static/description/index.html
odoo/addons/sale_loyalty_limit/tests/__init__.py
odoo/addons/sale_loyalty_limit/tests/test_sale_loyalty_limit.py
odoo_addon_sale_loyalty_limit-18.0.1.0.0.2.dist-info/METADATA
odoo_addon_sale_loyalty_limit-18.0.1.0.0.2.dist-info/WHEEL
odoo_addon_sale_loyalty_limit-18.0.1.0.0.2.dist-info/top_level.txt
odoo_addon_sale_loyalty_limit-18.0.1.0.0.2.dist-info/RECORD
